lockfile/__init__.py
lockfile/lockfile.py
tmplockfile-0.0.3.dist-info/DESCRIPTION.rst
tmplockfile-0.0.3.dist-info/METADATA
tmplockfile-0.0.3.dist-info/RECORD
tmplockfile-0.0.3.dist-info/WHEEL
tmplockfile-0.0.3.dist-info/metadata.json
tmplockfile-0.0.3.dist-info/top_level.txt
