Metadata-Version: 2.0
Name: tmplockfile
Version: 0.0.3
Summary: A minimal lock file mechanism
Home-page: https://github.com/jplusplus/lockfile
Author: Leo Wallentin | J++ Stockholm
Author-email: mejl@leowallentin.se
License: UNKNOWN
Platform: UNKNOWN
Classifier: Programming Language :: Python :: 3
Classifier: License :: OSI Approved :: MIT License
Classifier: Operating System :: OS Independent
